[{"_id":"a7d094df-bc61-4cfa-b398-b7c79ba9bca5","title":"Basic Info 2","description":"","questions":[{"_id":"c081c674-f68b-45dd-949e-7214816f3eb8","title":"What's your name?","description":"","type":"QUESTION_TEXT","content":{"placeHolder":"","inputType":"INPUT_TEXT","min":0,"max":512}},{"_id":"45f7e857-2728-4e46-977c-7c0657cc8861","title":"How old are you?","description":"","type":"QUESTION_SLIDER","content":{"min":2,"max":3,"minLabel":"minimum","maxLabel":"maximum","defaultValue":2,"step":1}}]}]